{
    "property": {
        "ANALYSIS_VERSION": "2.3.1.dev27",
        "TEMP": 20.0,
        "HUM": 0.0,
        "MEASUREMENT_DATE": "2025-02-13T15:41:56.000+00:00",
        "MEASUREMENT_DURATION": -1
    },
    "Metadata": {
        "MEASUREMENT_VERSION": null,
        "QC_LAYER": "L2",
        "INSTITUTION": "",
        "MODULE_SN": "20UPGS33301052"
    },
    "IV_ARRAY": {
        "time": [
            0,
            7,
            14,
            21,
            28,
            34,
            41,
            48,
            55,
            62,
            69,
            76,
            83,
            90,
            97,
            104,
            111,
            118,
            125,
            132,
            139,
            146,
            153,
            160,
            167,
            174,
            180,
            187,
            194,
            201,
            208,
            215,
            222,
            229,
            236,
            243,
            250,
            257,
            264,
            271,
            278
        ],
        "voltage": [
            0.0,
            5.0,
            10.0,
            15.0,
            20.0,
            25.0,
            30.0,
            35.0,
            40.0,
            45.0,
            50.0,
            55.0,
            60.0,
            65.0,
            70.0,
            75.0,
            80.0,
            85.0,
            90.0,
            95.0,
            100.0,
            105.0,
            110.0,
            115.0,
            120.0,
            125.0,
            130.0,
            135.0,
            140.0,
            145.0,
            150.0,
            155.0,
            160.0,
            165.0,
            170.0,
            175.0,
            180.0,
            185.0,
            190.0,
            195.0,
            200.0
        ],
        "current": [
            0.0293911,
            0.0995659,
            0.108719,
            0.11353700000000001,
            0.116412,
            0.118329,
            0.119664,
            0.12070199999999999,
            0.121615,
            0.12241800000000001,
            0.123059,
            0.12374900000000001,
            0.124143,
            0.12484200000000001,
            0.125361,
            0.125796,
            0.126344,
            0.126771,
            0.127407,
            0.127939,
            0.128307,
            0.12881800000000002,
            0.129466,
            0.12978099999999998,
            0.13027,
            0.130697,
            0.13112,
            0.131526,
            0.131919,
            0.13231700000000002,
            0.13272299999999998,
            0.133016,
            0.133409,
            0.856172,
            0.9129689999999999,
            0.9992350000000001,
            1.08537,
            1.17157,
            1.19827,
            1.23774,
            1.3064
        ],
        "sigma current": [
            0.0,
            0.0,
            0.0,
            0.0,
            0.0,
            0.0,
            0.0,
            0.0,
            0.0,
            0.0,
            0.0,
            0.0,
            0.0,
            0.0,
            0.0,
            0.0,
            0.0,
            0.0,
            0.0,
            0.0,
            0.0,
            0.0,
            0.0,
            0.0,
            0.0,
            0.0,
            0.0,
            0.0,
            0.0,
            0.0,
            0.0,
            0.0,
            0.0,
            0.0,
            0.0,
            0.0,
            0.0,
            0.0,
            0.0,
            0.0,
            0.0
        ],
        "temperature": [
            20,
            20,
            20,
            20,
            20,
            20,
            20,
            20,
            20,
            20,
            20,
            20,
            20,
            20,
            20,
            20,
            20,
            20,
            20,
            20,
            20,
            20,
            20,
            20,
            20,
            20,
            20,
            20,
            20,
            20,
            20,
            20,
            20,
            20,
            20,
            20,
            20,
            20,
            20,
            20,
            20
        ],
        "humidity": [
            0,
            0,
            0,
            0,
            0,
            0,
            0,
            0,
            0,
            0,
            0,
            0,
            0,
            0,
            0,
            0,
            0,
            0,
            0,
            0,
            0,
            0,
            0,
            0,
            0,
            0,
            0,
            0,
            0,
            0,
            0,
            0,
            0,
            0,
            0,
            0,
            0,
            0,
            0,
            0,
            0
        ]
    },
    "BREAKDOWN_VOLTAGE": 165.0,
    "BREAKDOWN_REDUCTION": -1164.0,
    "NO_BREAKDOWN_VOLTAGE_OBSERVED": false,
    "MAXIMUM_VOLTAGE": 200.0,
    "LEAK_CURRENT": 0.13027,
    "LEAK_INCREASE_FACTOR": 1.61,
    "LEAK_PER_AREA": 0.01
}